{
  "meta": {
    "build": {
      "build-date": "2021-03-19",
      "codified-date": "2021-02-16",
      "platform": {
        "reproducible": "true",
        "version": "2.1.4"
      },
      "repositories": [
        {
          "commit": "e9e6fcc05db8a9eb98bb25783f23e6d8cf1a90bb",
          "name": "mohicanlaw/law-xml"
        },
        {
          "commit": "2cc4b58ca680eda0c7a0da87c7894012b09cbaee",
          "name": "mohicanlaw/law-xml-codified"
        }
      ]
    },
    "canonical-urls": {
      "html": "https://law.mohican.com",
      "html-bulk": "https://github.com/mohicanlaw/law-html",
      "static-assets": "https://github.com/mohicanlaw/law-static-assets",
      "xml-bulk": "https://github.com/mohicanlaw/law-xml"
    },
    "contact": {
      "email": "help@openlawlib.org"
    },
    "description": "",
    "history-start": "2021-01-28"
  }
}